__init__.py
python_dev_cli/__init__.py
python_dev_cli/_version.py
python_dev_cli/cli.py
python_dev_cli/config.py
python_dev_cli/scripts.py
python_dev_cli/settings.py
python_dev_cli-1.1.0.dist-info/LICENSE
python_dev_cli-1.1.0.dist-info/METADATA
python_dev_cli-1.1.0.dist-info/WHEEL
python_dev_cli-1.1.0.dist-info/entry_points.txt
python_dev_cli-1.1.0.dist-info/top_level.txt
python_dev_cli-1.1.0.dist-info/RECORD
