Metadata-Version: 2.1
Name: python-dev-cli
Version: 1.1.0
Summary: Python developer CLI for running custom scripts defined in pyproject.toml
Author-email: Shaun Scovil <sscovil@pythondevcli.io>
License: BSD
Project-URL: Homepage, https://pythondevcli.io/
Project-URL: Documentation, https://github.com/sscovil/python-dev-cli/blob/main/README.md
Project-URL: Repository, https://github.com/sscovil/python-dev-cli
Project-URL: Issues, https://github.com/sscovil/python-dev-cli/issues
Project-URL: Changelog, https://github.com/sscovil/python-dev-cli/blob/main/CHANGELOG.md
Keywords: dev,cli,scripts,automation,config,pyproject.toml
Classifier: Development Status :: 5 - Production/Stable
Classifier: Environment :: Console
Classifier: Intended Audience :: Developers
Classifier: Intended Audience :: Information Technology
Classifier: Intended Audience :: System Administrators
Classifier: License :: OSI Approved :: BSD License
Classifier: Programming Language :: Python
Classifier: Programming Language :: Python :: 3
Classifier: Programming Language :: Python :: 3.11
Classifier: Programming Language :: Python :: 3.12
Classifier: Programming Language :: Python :: 3.13
Classifier: Programming Language :: Python :: 3 :: Only
Classifier: Natural Language :: English
Classifier: Operating System :: OS Independent
Classifier: Topic :: Software Development
Classifier: Topic :: Software Development :: Build Tools
Classifier: Topic :: Software Development :: Quality Assurance
Classifier: Topic :: Software Development :: Testing
Classifier: Topic :: System :: Systems Administration
Classifier: Topic :: Utilities
Classifier: Typing :: Typed
Requires-Python: >=3.11
License-File: LICENSE
Requires-Dist: jinja2 ~=3.1.2
Provides-Extra: dev
Requires-Dist: black ~=23.9.1 ; extra == 'dev'
Requires-Dist: pre-commit ~=3.4.0 ; extra == 'dev'
Requires-Dist: ruff ~=0.0.291 ; extra == 'dev'
Provides-Extra: publish
Requires-Dist: build ~=1.0.3 ; extra == 'publish'
Requires-Dist: twine ~=4.0.2 ; extra == 'publish'
